gmaltcli/__init__.py
gmaltcli/app.py
gmaltcli/database.py
gmaltcli/tools.py
gmaltcli/worker.py
gmaltcli/datasets/small.json
gmaltcli/datasets/srtm3.json
gmaltcli-1.1.0.dist-info/DESCRIPTION.rst
gmaltcli-1.1.0.dist-info/METADATA
gmaltcli-1.1.0.dist-info/RECORD
gmaltcli-1.1.0.dist-info/WHEEL
gmaltcli-1.1.0.dist-info/entry_points.txt
gmaltcli-1.1.0.dist-info/metadata.json
gmaltcli-1.1.0.dist-info/top_level.txt
