Metadata-Version: 2.0
Name: gmaltcli
Version: 1.1.0
Summary: Download, extract and import HGT data into a SQL database
Home-page: https://github.com/gmalt/cli
Author: Jonathan Bouzekri
Author-email: jonathan.bouzekri@gmail.com
License: MIT
Keywords: hgt,gis,cli,download,import
Platform: UNKNOWN
Classifier: Development Status :: 5 - Production/Stable
Classifier: Environment :: Console
Classifier: License :: OSI Approved :: MIT License
Classifier: Programming Language :: Python :: 2.7
Classifier: Programming Language :: Python :: 3.4
Classifier: Programming Language :: Python :: 3.5
Classifier: Programming Language :: Python :: 3.6
Classifier: Topic :: Scientific/Engineering :: GIS
Classifier: Topic :: Utilities
Requires-Dist: SQLAlchemy
Requires-Dist: psycopg2
Requires-Dist: future
Requires-Dist: gmalthgtparser
Provides-Extra: build
Requires-Dist: wheel; extra == 'build'
Provides-Extra: test
Requires-Dist: pytest; extra == 'test'
Requires-Dist: flake8; extra == 'test'
Requires-Dist: mock; extra == 'test'
Provides-Extra: tools
Requires-Dist: lxml; extra == 'tools'
